classtricks.py
setup.py
classtricks.egg-info/PKG-INFO
classtricks.egg-info/SOURCES.txt
classtricks.egg-info/dependency_links.txt
classtricks.egg-info/top_level.txt