Metadata-Version: 1.0
Name: classtricks
Version: 0.0.1421586552
Summary: A collection of simple tricks and helper functions for working with classes
Home-page: UNKNOWN
Author: Mike Lang
Author-email: mikelang3000@gmail.com
License: UNKNOWN
Platform: UNKNOWN
